ghostfolio/__init__.py
ghostfolio-0.8.0.dist-info/licenses/LICENSE
ghostfolio-0.8.0.dist-info/METADATA
ghostfolio-0.8.0.dist-info/WHEEL
ghostfolio-0.8.0.dist-info/entry_points.txt
ghostfolio-0.8.0.dist-info/top_level.txt
ghostfolio-0.8.0.dist-info/RECORD
