Metadata-Version: 2.4
Name: ghostfolio
Version: 0.8.0
Summary: Python API client for Ghostfolio
Author-email: Marcin Szymanski <ms32035@gmail.com>
Project-URL: Homepage, https://github.com/ms32035/ghostfolio-py
Requires-Python: >=3.10
License-File: LICENSE
Requires-Dist: requests
Dynamic: license-file
